TinyPc.sv
module TinyPc (
    input   wire    clock,
    input   wire    reset,
    input   wire    en_pc,
    output reg[7:0] addrout
);
    always @(posedge clock or posedge reset) begin
        if(reset) addrout <= 0;
        else if (en_pc) addrout <= addrout + 1;
    end
endmodule

TinyControl.sv
module TinyControl (
    input   wire    clock,
    input   wire    reset,

    input   wire    en_pc /* enable program counter */
);

    reg [2:0] state;
    reg [2:0] next_state;

    initial begin
        state = 0;
        next_state = 0;
    end

    always @(negedge clock) begin
        state <= next_state;
    end

    always @(posedge clock) begin

        if(!reset) begin
            next_state <= 0;
        end
        else begin
            case (state)
                1: begin
                    //fetch instruction from progmem
                    next_state <= 2;
                end
                2: begin
                    //inc the instrcution ptr
                    next_state <= 3;
                end
                3:begin
                    //do the instruciton
                    next_state <= 1;
                end
                default:next_state <= 1; 
            endcase
        end
    end
endmodule

TinyMcu.sv
module TinyMcu (
    input wire clock,
    input wire reset
);
  
    TinyControl Tc(.clock(clock), .reset(reset), .en_pc(en_pc));
    TinyPc Pc(.clock(clock), .reset(reset), .addrout(Pcaddrout), .en_pc(en_pc));
    
endmodule;

waveform.vcd
$version Generated by VerilatedVcd $end
$timescale 1ps $end
 $scope module TOP $end
  $var wire 1 # clock $end
  $var wire 1 $ reset $end
  $var wire 1 % en_pc $end
  $scope module TinyMcu $end
   $var wire 1 # clock $end
   $var wire 1 $ reset $end
   $var wire 1 % en_pc $end
   $var wire 8 & Pcaddrout [7:0] $end
   $scope module Pc $end
    $var wire 1 # clock $end
    $var wire 1 $ reset $end
    $var wire 1 % en_pc $end
    $var wire 8 & addrout [7:0] $end
   $upscope $end
  $upscope $end
 $upscope $end
$enddefinitions $end


#0
1#
0$
1%
b00000000 &
#1
0#
#2
1#
b00000001 &
#3
0#
#4
1#
b00000010 &
#5
0#
#6
1#
b00000011 &
#7
0#
#8
1#
b00000100 &
#9
0#
#10
1#
b00000101 &
#11
0#
#12
1#
b00000110 &
#13
0#
#14
1#
b00000111 &
#15
0#
#16
1#
b00001000 &
#17
0#
#18
1#
b00001001 &
#19
0#
#20
1#
b00001010 &
#21
0#
#22
1#
b00001011 &
#23
0#
#24
1#
b00001100 &
#25
0#
#26
1#
b00001101 &
#27
0#
#28
1#
b00001110 &
#29
0#
#30
1#
b00001111 &
#31
0#
#32
1#
b00010000 &
#33
0#
#34
1#
b00010001 &
#35
0#
#36
1#
b00010010 &
#37
0#
#38
1#
b00010011 &
#39
0#
#40
1#
b00010100 &
#41
0#
#42
1#
b00010101 &
#43
0#
#44
1#
b00010110 &
#45
0#
#46
1#
b00010111 &
#47
0#
#48
1#
b00011000 &
#49
0#
#50
1#
b00011001 &
#51
0#
#52
1#
b00011010 &
#53
0#
#54
1#
b00011011 &
#55
0#
#56
1#
b00011100 &
#57
0#
#58
1#
b00011101 &
#59
0#
#60
1#
b00011110 &
#61
0#
#62
1#
b00011111 &
#63
0#
#64
1#
b00100000 &
#65
0#
#66
1#
b00100001 &
#67
0#
#68
1#
b00100010 &
#69
0#
#70
1#
b00100011 &
#71
0#
#72
1#
b00100100 &
#73
0#
#74
1#
b00100101 &
#75
0#
#76
1#
b00100110 &
#77
0#
#78
1#
b00100111 &
#79
0#
#80
1#
b00101000 &
#81
0#
#82
1#
b00101001 &
#83
0#
#84
1#
b00101010 &
#85
0#
#86
1#
b00101011 &
#87
0#
#88
1#
b00101100 &
#89
0#
#90
1#
b00101101 &
#91
0#
#92
1#
b00101110 &
#93
0#
#94
1#
b00101111 &
#95
0#
#96
1#
b00110000 &
#97
0#
#98
1#
b00110001 &
#99
0#
#100
1#
b00110010 &
#101
0#
#102
1#
b00110011 &
#103
0#
#104
1#
b00110100 &
#105
0#
#106
1#
b00110101 &
#107
0#
#108
1#
b00110110 &
#109
0#
#110
1#
b00110111 &
#111
0#
#112
1#
b00111000 &
#113
0#
#114
1#
b00111001 &
#115
0#
#116
1#
b00111010 &
#117
0#
#118
1#
b00111011 &
#119
0#
#120
1#
b00111100 &
#121
0#
#122
1#
b00111101 &
#123
0#
#124
1#
b00111110 &
#125
0#
#126
1#
b00111111 &
#127
0#
#128
1#
b01000000 &
#129
0#
#130
1#
b01000001 &
#131
0#
#132
1#
b01000010 &
#133
0#
#134
1#
b01000011 &
#135
0#
#136
1#
b01000100 &
#137
0#
#138
1#
b01000101 &
#139
0#
#140
1#
b01000110 &
#141
0#
#142
1#
b01000111 &
#143
0#
#144
1#
b01001000 &
#145
0#
#146
1#
b01001001 &
#147
0#
#148
1#
b01001010 &
#149
0#
#150
1#
b01001011 &
#151
0#
#152
1#
b01001100 &
#153
0#
#154
1#
b01001101 &
#155
0#
#156
1#
b01001110 &
#157
0#
#158
1#
b01001111 &
#159
0#
#160
1#
b01010000 &
#161
0#
#162
1#
b01010001 &
#163
0#
#164
1#
b01010010 &
#165
0#
#166
1#
b01010011 &
#167
0#
#168
1#
b01010100 &
#169
0#
#170
1#
b01010101 &
#171
0#
#172
1#
b01010110 &
#173
0#
#174
1#
b01010111 &
#175
0#
#176
1#
b01011000 &
#177
0#
#178
1#
b01011001 &
#179
0#
#180
1#
b01011010 &
#181
0#
#182
1#
b01011011 &
#183
0#
#184
1#
b01011100 &
#185
0#
#186
1#
b01011101 &
#187
0#
#188
1#
b01011110 &
#189
0#
#190
1#
b01011111 &
#191
0#
#192
1#
b01100000 &
#193
0#
#194
1#
b01100001 &
#195
0#
#196
1#
b01100010 &
#197
0#
#198
1#
b01100011 &
#199
0#
#200
1#
b01100100 &
#201
0#
#202
1#
b01100101 &
#203
0#
#204
1#
b01100110 &
#205
0#
#206
1#
b01100111 &
#207
0#
#208
1#
b01101000 &
#209
0#
#210
1#
b01101001 &
#211
0#
#212
1#
b01101010 &
#213
0#
#214
1#
b01101011 &
#215
0#
#216
1#
b01101100 &
#217
0#
#218
1#
b01101101 &
#219
0#
#220
1#
b01101110 &
#221
0#
#222
1#
b01101111 &
#223
0#
#224
1#
b01110000 &
#225
0#
#226
1#
b01110001 &
#227
0#
#228
1#
b01110010 &
#229
0#
#230
1#
b01110011 &
#231
0#
#232
1#
b01110100 &
#233
0#
#234
1#
b01110101 &
#235
0#
#236
1#
b01110110 &
#237
0#
#238
1#
b01110111 &
#239
0#
#240
1#
b01111000 &
#241
0#
#242
1#
b01111001 &
#243
0#
#244
1#
b01111010 &
#245
0#
#246
1#
b01111011 &
#247
0#
#248
1#
b01111100 &
#249
0#
#250
1#
b01111101 &
#251
0#
#252
1#
b01111110 &
#253
0#
#254
1#
b01111111 &
#255
0#
#256
1#
b10000000 &
#257
0#
#258
1#
b10000001 &
#259
0#
#260
1#
b10000010 &
#261
0#
#262
1#
b10000011 &
#263
0#
#264
1#
b10000100 &
#265
0#
#266
1#
b10000101 &
#267
0#
#268
1#
b10000110 &
#269
0#
#270
1#
b10000111 &
#271
0#
#272
1#
b10001000 &
#273
0#
#274
1#
b10001001 &
#275
0#
#276
1#
b10001010 &
#277
0#
#278
1#
b10001011 &
#279
0#
#280
1#
b10001100 &
#281
0#
#282
1#
b10001101 &
#283
0#
#284
1#
b10001110 &
#285
0#
#286
1#
b10001111 &
#287
0#
#288
1#
b10010000 &
#289
0#
#290
1#
b10010001 &
#291
0#
#292
1#
b10010010 &
#293
0#
#294
1#
b10010011 &
#295
0#
#296
1#
b10010100 &
#297
0#
#298
1#
b10010101 &
